{"last_node_id":826,"last_link_id":1472,"nodes":[{"id":699,"type":"GroundingDinoModelLoader (segment anything)","pos":[845.9689148242514,-1279.5630879400715],"size":{"0":455.3423156738281,"1":91.98837280273438},"flags":{},"order":0,"mode":0,"outputs":[{"name":"GROUNDING_DINO_MODEL","type":"GROUNDING_DINO_MODEL","links":[1248],"shape":3,"label":"GROUNDING_DINO_MODEL"}],"properties":{"Node name for S&R":"GroundingDinoModelLoader (segment anything)"},"widgets_values":["GroundingDINO_SwinT_OGC (694MB)"],"serialize_values":[null]},{"id":700,"type":"PreviewImage","pos":[1325.9689148242533,-1219.5630879400715],"size":{"0":229.08111572265625,"1":293.6535949707031},"flags":{},"order":57,"mode":0,"inputs":[{"name":"images","type":"IMAGE","link":1250,"label":"images"}],"properties":{"Node name for S&R":"PreviewImage"}},{"id":708,"type":"JoinImageWithAlpha","pos":[1565.9689148242533,-1149.5630879400715],"size":{"0":241.5544891357422,"1":51.13587188720703},"flags":{},"order":59,"mode":0,"inputs":[{"name":"image","type":"IMAGE","link":1256,"label":"image"},{"name":"alpha","type":"MASK","link":1275,"label":"alpha"}],"outputs":[{"name":"IMAGE","type":"IMAGE","links":[1271,1415],"shape":3,"label":"IMAGE","slot_index":0}],"properties":{"Node name for S&R":"JoinImageWithAlpha"}},{"id":718,"type":"SplitImageWithAlpha","pos":[1565.9689148242533,-1049.5630879400715],"size":{"0":237.40045166015625,"1":47.23573684692383},"flags":{},"order":60,"mode":0,"inputs":[{"name":"image","type":"IMAGE","link":1271,"label":"image"}],"outputs":[{"name":"IMAGE","type":"IMAGE","links":[1273],"shape":3,"label":"IMAGE","slot_index":0},{"name":"MASK","type":"MASK","links":[1272],"shape":3,"label":"MASK","slot_index":1}],"properties":{"Node name for S&R":"SplitImageWithAlpha"}},{"id":720,"type":"Mask Invert","pos":[1565.9689148242533,-1219.5630879400715],"size":{"0":242.593017578125,"1":26.151613235473633},"flags":{},"order":58,"mode":0,"inputs":[{"name":"masks","type":"MASK","link":1274,"label":"masks"}],"outputs":[{"name":"MASKS","type":"MASK","links":[1275],"shape":3,"label":"MASKS","slot_index":0}],"properties":{"Node name for S&R":"Mask Invert"}},{"id":734,"type":"Reroute","pos":[751.8658425558743,-31.703830295138903],"size":[140.8,26],"flags":{},"order":50,"mode":0,"inputs":[{"name":"","type":"*","link":1418,"label":""}],"outputs":[{"name":"CONDITIONING","type":"CONDITIONING","links":[1303],"slot_index":0,"label":"CONDITIONING"}],"properties":{"showOutputText":true,"horizontal":false}},{"id":735,"type":"Reroute","pos":[751.8658425558743,8.296169704861095],"size":[140.8,26],"flags":{},"order":52,"mode":0,"inputs":[{"name":"","type":"*","link":1419,"label":""}],"outputs":[{"name":"CONDITIONING","type":"CONDITIONING","links":[1304],"slot_index":0,"label":"CONDITIONING"}],"properties":{"showOutputText":true,"horizontal":false}},{"id":647,"type":"CLIPTextEncode","pos":[-1295,-506],"size":{"0":210,"1":54},"flags":{},"order":42,"mode":0,"inputs":[{"name":"clip","type":"CLIP","link":1172,"label":"clip"},{"name":"text","type":"STRING","link":1193,"widget":{"name":"text"},"label":"text"}],"outputs":[{"name":"CONDITIONING","type":"CONDITIONING","links":[1205],"shape":3,"label":"CONDITIONING","slot_index":0}],"properties":{"Node name for S&R":"CLIPTextEncode"},"widgets_values":["1boy,chinese festival, red background,cute, 3d,masterpiece,best quality,"],"serialize_values":["1boy,chinese festival, red background,cute, 3d,masterpiece,best quality,"]},{"id":681,"type":"ControlNetApplyAdvanced","pos":[-1286.6499321831432,206.95421569165188],"size":{"0":435.32513427734375,"1":166},"flags":{},"order":46,"mode":0,"inputs":[{"name":"positive","type":"CONDITIONING","link":1205,"label":"positive"},{"name":"negative","type":"CONDITIONING","link":1206,"label":"negative"},{"name":"control_net","type":"CONTROL_NET","link":1204,"label":"control_net","slot_index":2},{"name":"image","type":"IMAGE","link":1201,"label":"image"}],"outputs":[{"name":"positive","type":"CONDITIONING","links":[1383],"shape":3,"label":"positive","slot_index":0},{"name":"negative","type":"CONDITIONING","links":[1384],"shape":3,"label":"negative","slot_index":1}],"properties":{"Node name for S&R":"ControlNetApplyAdvanced"},"widgets_values":[1,0,0.75],"serialize_values":[null,null,null]},{"id":673,"type":"GetImageSize","pos":[-1756.6499321831432,166.9542156916518],"size":{"0":438.5289611816406,"1":65.36558532714844},"flags":{},"order":31,"mode":0,"inputs":[{"name":"image","type":"IMAGE","link":1225,"label":"image"}],"outputs":[{"name":"width","type":"INT","links":[1218,1239,1388],"shape":3,"label":"width","slot_index":0},{"name":"height","type":"INT","links":[1219,1240,1389],"shape":3,"label":"height","slot_index":1}],"properties":{"Node name for S&R":"GetImageSize"}},{"id":780,"type":"Load RetinaFace","pos":[-1284,-1388],"size":{"0":405.4595031738281,"1":27.24616813659668},"flags":{},"order":1,"mode":0,"outputs":[{"name":"MODEL","type":"RETINAFACE","links":[1395],"shape":3,"label":"MODEL"}],"properties":{"Node name for S&R":"Load RetinaFace"}},{"id":772,"type":"Reroute","pos":[-1890,-1466],"size":[82,26],"flags":{},"order":15,"mode":0,"inputs":[{"name":"","type":"*","link":1379,"label":""}],"outputs":[{"name":"IMAGE","type":"IMAGE","links":[1396],"slot_index":0,"label":"IMAGE"}],"properties":{"showOutputText":true,"horizontal":false}},{"id":670,"type":"Reroute","pos":[-1901,-107],"size":[82,26],"flags":{},"order":17,"mode":0,"inputs":[{"name":"","type":"*","link":1399,"label":""}],"outputs":[{"name":"IMAGE","type":"IMAGE","links":[1198],"slot_index":0,"label":"IMAGE"}],"properties":{"showOutputText":true,"horizontal":false}},{"id":677,"type":"Image scale to side","pos":[-1756.6499321831432,-13.045784308348075],"size":{"0":439.1317138671875,"1":130},"flags":{},"order":25,"mode":0,"inputs":[{"name":"image","type":"IMAGE","link":1198,"label":"image"}],"outputs":[{"name":"IMAGE","type":"IMAGE","links":[1225,1226,1227,1385,1387],"shape":3,"label":"IMAGE","slot_index":0}],"properties":{"Node name for S&R":"Image scale to side"},"widgets_values":[1024,"Longest","nearest-exact","disabled"],"serialize_values":[null,null,null,null]},{"id":788,"type":"Image scale to side","pos":[845.9689148242514,-1139.5630879400715],"size":{"0":458.5540466308594,"1":130},"flags":{},"order":26,"mode":0,"inputs":[{"name":"image","type":"IMAGE","link":1413,"label":"image"}],"outputs":[{"name":"IMAGE","type":"IMAGE","links":[1411,1412],"shape":3,"label":"IMAGE","slot_index":0}],"properties":{"Node name for S&R":"Image scale to side"},"widgets_values":[1024,"Longest","nearest-exact","disabled"],"serialize_values":[null,null,null,null]},{"id":715,"type":"GetImageSize","pos":[845.9689148242514,-959.5630879400713],"size":{"0":459.0335388183594,"1":47.674888610839844},"flags":{},"order":32,"mode":0,"inputs":[{"name":"image","type":"IMAGE","link":1411,"label":"image"}],"outputs":[{"name":"width","type":"INT","links":[1409],"shape":3,"label":"width","slot_index":0},{"name":"height","type":"INT","links":[1410],"shape":3,"label":"height","slot_index":1}],"properties":{"Node name for S&R":"GetImageSize"}},{"id":716,"type":"PreviewImage","pos":[1395.9689148242533,-869.5630879400713],"size":{"0":406.2677917480469,"1":518.727783203125},"flags":{},"order":63,"mode":0,"inputs":[{"name":"images","type":"IMAGE","link":1269,"label":"images"}],"properties":{"Node name for S&R":"PreviewImage"}},{"id":786,"type":"Reroute","pos":[665.9689148242514,-1359.5630879400715],"size":[82,26],"flags":{},"order":18,"mode":0,"inputs":[{"name":"","type":"*","link":1403,"label":""}],"outputs":[{"name":"IMAGE","type":"IMAGE","links":[1413],"label":"IMAGE","slot_index":0}],"properties":{"showOutputText":true,"horizontal":false}},{"id":695,"type":"GroundingDinoSAMSegment (segment anything)","pos":[1335.9689148242533,-1379.5630879400715],"size":{"0":486.9090270996094,"1":122},"flags":{},"order":56,"mode":0,"inputs":[{"name":"sam_model","type":"SAM_MODEL","link":1251,"label":"sam_model","slot_index":0},{"name":"grounding_dino_model","type":"GROUNDING_DINO_MODEL","link":1248,"label":"grounding_dino_model","slot_index":1},{"name":"image","type":"IMAGE","link":1406,"label":"image"}],"outputs":[{"name":"IMAGE","type":"IMAGE","links":[1250,1256],"shape":3,"label":"IMAGE","slot_index":0},{"name":"MASK","type":"MASK","links":[1274],"shape":3,"label":"MASK","slot_index":1}],"properties":{"Node name for S&R":"GroundingDinoSAMSegment (segment anything)"},"widgets_values":["1person,",0.3],"serialize_values":[null,null]},{"id":787,"type":"Reroute","pos":[665.9689148242514,-1409.5630879400715],"size":[82,26],"flags":{},"order":55,"mode":0,"inputs":[{"name":"","type":"*","link":1421,"label":""}],"outputs":[{"name":"IMAGE","type":"IMAGE","links":[1406],"slot_index":0,"label":"IMAGE"}],"properties":{"showOutputText":true,"horizontal":false}},{"id":725,"type":"Reroute","pos":[811.8658425558743,-201.7038302951389],"size":[82,26],"flags":{},"order":64,"mode":0,"inputs":[{"name":"","type":"*","link":1416,"label":""}],"outputs":[{"name":"IMAGE","type":"IMAGE","links":[1284],"slot_index":0,"label":"IMAGE"}],"properties":{"showOutputText":true,"horizontal":false}},{"id":717,"type":"PreviewImage","pos":[1145.9689148242533,-869.5630879400713],"size":{"0":222.41375732421875,"1":284.0551452636719},"flags":{},"order":61,"mode":0,"inputs":[{"name":"images","type":"IMAGE","link":1415,"label":"images"}],"properties":{"Node name for S&R":"PreviewImage"}},{"id":714,"type":"Image Overlay","pos":[845.9689148242514,-869.5630879400713],"size":{"0":284.0042724609375,"1":282},"flags":{},"order":62,"mode":0,"inputs":[{"name":"base_image","type":"IMAGE","link":1412,"label":"base_image"},{"name":"overlay_image","type":"IMAGE","link":1273,"label":"overlay_image"},{"name":"optional_mask","type":"MASK","link":1272,"label":"optional_mask"},{"name":"width","type":"INT","link":1409,"widget":{"name":"width"},"label":"width"},{"name":"height","type":"INT","link":1410,"widget":{"name":"height"},"label":"height"}],"outputs":[{"name":"IMAGE","type":"IMAGE","links":[1269,1416],"shape":3,"label":"IMAGE","slot_index":0}],"properties":{"Node name for S&R":"Image Overlay"},"widgets_values":["None","nearest-exact",1,512,512,0,0,0,0],"color":"#223322","bgcolor":"#553355","shape":2,"serialize_values":[null,null,null,null,null,null,null,null,null]},{"id":648,"type":"CLIPTextEncode","pos":[-1067,-506],"size":{"0":210,"1":54},"flags":{},"order":43,"mode":0,"inputs":[{"name":"clip","type":"CLIP","link":1173,"label":"clip"},{"name":"text","type":"STRING","link":1194,"widget":{"name":"text"},"label":"text"}],"outputs":[{"name":"CONDITIONING","type":"CONDITIONING","links":[1206],"shape":3,"label":"CONDITIONING","slot_index":0}],"properties":{"Node name for S&R":"CLIPTextEncode"},"widgets_values":["normal quality,bad quality, worse quality,ugly,signature, "],"serialize_values":["normal quality,bad quality, worse quality,ugly,signature, "]},{"id":739,"type":"PreviewImage","pos":[1332.5557318793392,-99.70383029513891],"size":{"0":457.1552429199219,"1":589.2269897460938},"flags":{},"order":69,"mode":0,"inputs":[{"name":"images","type":"IMAGE","link":1311,"label":"images"}],"properties":{"Node name for S&R":"PreviewImage"}},{"id":687,"type":"Reroute","pos":[-165,173],"size":[140.8,26],"flags":{},"order":48,"mode":0,"inputs":[{"name":"","type":"*","link":1392,"label":""}],"outputs":[{"name":"CONDITIONING","type":"CONDITIONING","links":[1215,1418],"slot_index":0,"label":"CONDITIONING"}],"properties":{"showOutputText":true,"horizontal":false}},{"id":688,"type":"Reroute","pos":[-166,210],"size":[140.8,26],"flags":{},"order":49,"mode":0,"inputs":[{"name":"","type":"*","link":1393,"label":""}],"outputs":[{"name":"CONDITIONING","type":"CONDITIONING","links":[1216,1419],"slot_index":0,"label":"CONDITIONING"}],"properties":{"showOutputText":true,"horizontal":false}},{"id":649,"type":"EmptyLatentImage","pos":[-752.4794194975968,-526.0055556072225],"size":{"0":490.10797119140625,"1":92.3214340209961},"flags":{},"order":35,"mode":0,"inputs":[{"name":"width","type":"INT","link":1239,"widget":{"name":"width"},"label":"width"},{"name":"height","type":"INT","link":1240,"widget":{"name":"height"},"label":"height"}],"outputs":[{"name":"LATENT","type":"LATENT","links":[1167],"shape":3,"label":"LATENT"}],"properties":{"Node name for S&R":"EmptyLatentImage"},"widgets_values":[1024,1024,1],"serialize_values":[null,null,null]},{"id":652,"type":"PreviewImage","pos":[-219,-1291],"size":{"0":782.52734375,"1":1130.3875732421875},"flags":{},"order":54,"mode":0,"inputs":[{"name":"images","type":"IMAGE","link":1175,"label":"images"}],"properties":{"Node name for S&R":"PreviewImage"}},{"id":737,"type":"LatentUpscaleBy","pos":[1001.865842555874,-101.70383029513891],"size":{"0":315,"1":82},"flags":{},"order":66,"mode":0,"inputs":[{"name":"samples","type":"LATENT","link":1306,"label":"samples"}],"outputs":[{"name":"LATENT","type":"LATENT","links":[1308],"shape":3,"label":"LATENT","slot_index":0}],"properties":{"Node name for S&R":"LatentUpscaleBy"},"widgets_values":["nearest-exact",1.5],"serialize_values":[null,null]},{"id":733,"type":"Reroute","pos":[812,-152],"size":[82,26],"flags":{},"order":41,"mode":0,"inputs":[{"name":"","type":"*","link":1417,"label":""}],"outputs":[{"name":"MODEL","type":"MODEL","links":[1302],"slot_index":0,"label":"MODEL"}],"properties":{"showOutputText":true,"horizontal":false}},{"id":775,"type":"CannyEdgePreprocessor","pos":[-736.6499321831428,256.95421569165205],"size":{"0":383.6854553222656,"1":106},"flags":{},"order":40,"mode":0,"inputs":[{"name":"image","type":"IMAGE","link":1385,"label":"image"},{"name":"resolution","type":"INT","link":1390,"widget":{"name":"resolution"},"label":"resolution"}],"outputs":[{"name":"IMAGE","type":"IMAGE","links":[1391,1423],"shape":3,"label":"IMAGE","slot_index":0}],"properties":{"Node name for S&R":"CannyEdgePreprocessor"},"widgets_values":[100,200,512],"serialize_values":[null,null,null]},{"id":790,"type":"PreviewImage","pos":[-736,419],"size":{"0":210,"1":246},"flags":{},"order":45,"mode":0,"inputs":[{"name":"images","type":"IMAGE","link":1423,"label":"images"}],"properties":{"Node name for S&R":"PreviewImage"}},{"id":791,"type":"PreviewImage","pos":[-1283,440],"size":{"0":210,"1":246},"flags":{},"order":44,"mode":0,"inputs":[{"name":"images","type":"IMAGE","link":1424,"label":"images"}],"properties":{"Node name for S&R":"PreviewImage"}},{"id":773,"type":"ControlNetApplyAdvanced","pos":[-336.6499321831426,-3.0457843083480793],"size":{"0":315,"1":166},"flags":{},"order":47,"mode":0,"inputs":[{"name":"positive","type":"CONDITIONING","link":1383,"label":"positive"},{"name":"negative","type":"CONDITIONING","link":1384,"label":"negative"},{"name":"control_net","type":"CONTROL_NET","link":1381,"label":"control_net","slot_index":2},{"name":"image","type":"IMAGE","link":1391,"label":"image","slot_index":3}],"outputs":[{"name":"positive","type":"CONDITIONING","links":[1392],"shape":3,"label":"positive","slot_index":0},{"name":"negative","type":"CONDITIONING","links":[1393],"shape":3,"label":"negative","slot_index":1}],"properties":{"Node name for S&R":"ControlNetApplyAdvanced"},"widgets_values":[0.5,0,0.5],"serialize_values":[null,null,null]},{"id":738,"type":"VAEDecode","pos":[1340.5557318793392,-199.7038302951389],"size":{"0":392.27728271484375,"1":50.094181060791016},"flags":{},"order":68,"mode":0,"inputs":[{"name":"samples","type":"LATENT","link":1309,"label":"samples"},{"name":"vae","type":"VAE","link":1310,"label":"vae"}],"outputs":[{"name":"IMAGE","type":"IMAGE","links":[1311,1425],"shape":3,"label":"IMAGE","slot_index":0}],"properties":{"Node name for S&R":"VAEDecode"}},{"id":795,"type":"GetImageSize","pos":[2065.584027287317,-1355.4969660560387],"size":{"0":210,"1":46},"flags":{},"order":71,"mode":0,"inputs":[{"name":"image","type":"IMAGE","link":1431,"label":"image"}],"outputs":[{"name":"width","type":"INT","links":[1428],"shape":3,"label":"width","slot_index":0},{"name":"height","type":"INT","links":[1429],"shape":3,"label":"height","slot_index":1}],"properties":{"Node name for S&R":"GetImageSize"}},{"id":792,"type":"Reroute","pos":[1914.584027287316,-1380.4969660560387],"size":[82,26],"flags":{},"order":70,"mode":0,"inputs":[{"name":"","type":"*","link":1425,"label":""}],"outputs":[{"name":"IMAGE","type":"IMAGE","links":[1430,1431],"slot_index":0,"label":"IMAGE"}],"properties":{"showOutputText":true,"horizontal":false}},{"id":726,"type":"VAEEncode","pos":[1102,-202],"size":{"0":210,"1":46},"flags":{},"order":65,"mode":0,"inputs":[{"name":"pixels","type":"IMAGE","link":1284,"label":"pixels"},{"name":"vae","type":"VAE","link":1301,"label":"vae","slot_index":1}],"outputs":[{"name":"LATENT","type":"LATENT","links":[1306],"shape":3,"label":"LATENT","slot_index":0}],"properties":{"Node name for S&R":"VAEEncode"}},{"id":729,"type":"KSampler","pos":[1001.865842555874,18.296169704861097],"size":{"0":316.9495544433594,"1":474},"flags":{},"order":67,"mode":0,"inputs":[{"name":"model","type":"MODEL","link":1302,"label":"model"},{"name":"positive","type":"CONDITIONING","link":1303,"label":"positive","slot_index":1},{"name":"negative","type":"CONDITIONING","link":1304,"label":"negative","slot_index":2},{"name":"latent_image","type":"LATENT","link":1308,"label":"latent_image"}],"outputs":[{"name":"LATENT","type":"LATENT","links":[1309],"shape":3,"label":"LATENT","slot_index":0}],"properties":{"Node name for S&R":"KSampler"},"widgets_values":[346257464615026,"randomize",20,7,"euler","normal",0.5],"serialize_values":[null,null,null,null,null,null,null]},{"id":781,"type":"PreviewImage","pos":[-1286,-1155],"size":{"0":409.3904113769531,"1":246},"flags":{},"order":28,"mode":0,"inputs":[{"name":"images","type":"IMAGE","link":1398,"label":"images"}],"properties":{"Node name for S&R":"PreviewImage"}},{"id":663,"type":"SDXLPromptStyler","pos":[-1755,-346],"size":{"0":433.6637878417969,"1":182},"flags":{},"order":14,"mode":0,"inputs":[{"name":"text_positive","type":"STRING","link":1186,"widget":{"name":"text_positive"},"label":"text_positive"},{"name":"text_negative","type":"STRING","link":1187,"widget":{"name":"text_negative"},"label":"text_negative"}],"outputs":[{"name":"text_positive","type":"STRING","links":[1191],"shape":3,"label":"text_positive","slot_index":0},{"name":"text_negative","type":"STRING","links":[1192],"shape":3,"label":"text_negative","slot_index":1}],"properties":{"Node name for S&R":"SDXLPromptStyler"},"widgets_values":["1boy,chinese festival, red background,cute, 3d,masterpiece,best quality,","normal quality,bad quality, worse quality,ugly,signature, ","sai-anime",false],"serialize_values":["1boy,chinese festival, red background,cute, 3d,masterpiece,best quality,","normal quality,bad quality, worse quality,ugly,signature, ",null,null]},{"id":667,"type":"ShowText|pysssss","pos":[-1295,-646],"size":{"0":445.2095642089844,"1":93.89286041259766},"flags":{},"order":22,"mode":0,"inputs":[{"name":"text","type":"STRING","link":1192,"widget":{"name":"text"},"label":"text"}],"outputs":[{"name":"STRING","type":"STRING","links":[1194],"shape":6,"label":"STRING","slot_index":0}],"properties":{"Node name for S&R":"ShowText|pysssss"},"widgets_values":["","photo, deformed, black and white, realism, disfigured, low contrast, ugly, deformed, noisy, low poly, blurry, painting, hand,normal quality,bad quality, worse quality,ugly,signature, "],"serialize_values":["",null]},{"id":666,"type":"ShowText|pysssss","pos":[-1295.0955615707207,-806.3917462808859],"size":{"0":441.7581481933594,"1":106.07879638671875},"flags":{},"order":21,"mode":0,"inputs":[{"name":"text","type":"STRING","link":1191,"widget":{"name":"text"},"label":"text"}],"outputs":[{"name":"STRING","type":"STRING","links":[1193],"shape":6,"label":"STRING","slot_index":0}],"properties":{"Node name for S&R":"ShowText|pysssss"},"widgets_values":["","anime artwork professional 3d model a human,happy,upper_body,focus on face, firecrackers, fireworks, lantern, Chinese festival, dark background, night,depth of field,fcartoon, 3d style, Pixar Animation Studio, simple background, fantastic,solo, unity, masterpiece,best quality, . octane render, highly detailed, volumetric, dramatic lighting . anime style, key visual, vibrant, studio anime, highly detailed"],"serialize_values":["",null]},{"id":811,"type":"Reroute","pos":[1962.9611914942955,-216.58909803368573],"size":[82,26],"flags":{},"order":74,"mode":0,"inputs":[{"name":"","type":"*","link":1462,"label":""}],"outputs":[{"name":"IMAGE","type":"IMAGE","links":[1448,1449],"slot_index":0,"label":"IMAGE"}],"properties":{"showOutputText":true,"horizontal":false}},{"id":819,"type":"Reroute","pos":[1962.9611914942955,-176.589098033686],"size":[90.4,26],"flags":{},"order":16,"mode":0,"inputs":[{"name":"","type":"*","link":1459,"label":"","widget":{"name":"value"}}],"outputs":[{"name":"STRING","type":"STRING","links":[1458],"slot_index":0,"label":"*"}],"properties":{"showOutputText":true,"horizontal":false}},{"id":810,"type":"GetImageSize","pos":[2082.961191494292,-186.589098033686],"size":{"0":365.9239196777344,"1":47.96207809448242},"flags":{},"order":75,"mode":0,"inputs":[{"name":"image","type":"IMAGE","link":1448,"label":"image"}],"outputs":[{"name":"width","type":"INT","links":[1454],"shape":3,"label":"width","slot_index":0},{"name":"height","type":"INT","links":null,"shape":3,"label":"height","slot_index":1}],"properties":{"Node name for S&R":"GetImageSize"}},{"id":813,"type":"GetImageSize","pos":[2472.961191494292,-186.589098033686],"size":{"0":210,"1":46},"flags":{},"order":30,"mode":0,"inputs":[{"name":"image","type":"IMAGE","link":1450,"label":"image"}],"outputs":[{"name":"width","type":"INT","links":[1453],"shape":3,"label":"width","slot_index":0},{"name":"height","type":"INT","links":null,"shape":3,"label":"height"}],"properties":{"Node name for S&R":"GetImageSize"}},{"id":808,"type":"SplitImageWithAlpha","pos":[2472.961191494292,-96.58909803368697],"size":{"0":210,"1":46},"flags":{},"order":29,"mode":0,"inputs":[{"name":"image","type":"IMAGE","link":1444,"label":"image"}],"outputs":[{"name":"IMAGE","type":"IMAGE","links":[1445],"shape":3,"label":"IMAGE","slot_index":0},{"name":"MASK","type":"MASK","links":[1446],"shape":3,"label":"MASK","slot_index":1}],"properties":{"Node name for S&R":"SplitImageWithAlpha"}},{"id":812,"type":"CM_IntBinaryOperation","pos":[2702.961191494293,-186.589098033686],"size":{"0":210,"1":78},"flags":{},"order":76,"mode":0,"inputs":[{"name":"a","type":"INT","link":1454,"widget":{"name":"a"},"label":"a"},{"name":"b","type":"INT","link":1453,"widget":{"name":"b"},"label":"b"}],"outputs":[{"name":"INT","type":"INT","links":[1455],"shape":3,"label":"INT","slot_index":0}],"properties":{"Node name for S&R":"CM_IntBinaryOperation"},"widgets_values":["Sub",0,0],"serialize_values":[null,null,null]},{"id":814,"type":"CM_IntBinaryOperation","pos":[2702.961191494293,-66.58909803368687],"size":{"0":210,"1":82},"flags":{},"order":77,"mode":0,"inputs":[{"name":"a","type":"INT","link":1455,"widget":{"name":"a"},"label":"a"}],"outputs":[{"name":"INT","type":"INT","links":[1456],"shape":3,"label":"INT","slot_index":0}],"properties":{"Node name for S&R":"CM_IntBinaryOperation"},"widgets_values":["Div",0,2],"serialize_values":[null,null,null]},{"id":806,"type":"Image Overlay","pos":[2482.961191494292,63.41090196631301],"size":{"0":431.04949951171875,"1":309.0103454589844},"flags":{},"order":78,"mode":0,"inputs":[{"name":"base_image","type":"IMAGE","link":1449,"label":"base_image"},{"name":"overlay_image","type":"IMAGE","link":1445,"label":"overlay_image"},{"name":"optional_mask","type":"MASK","link":1446,"label":"optional_mask"},{"name":"x_offset","type":"INT","link":1456,"widget":{"name":"x_offset"},"label":"x_offset"}],"outputs":[{"name":"IMAGE","type":"IMAGE","links":[1441,1460],"shape":3,"label":"IMAGE","slot_index":0}],"properties":{"Node name for S&R":"Image Overlay"},"widgets_values":["None","nearest-exact",1,512,512,300,0,0,0],"color":"#222233","bgcolor":"#665533","shape":1,"serialize_values":[null,null,null,null,null,null,null,null,null]},{"id":701,"type":"SAMModelLoader (segment anything)","pos":[855.9689148242514,-1389.5630879400715],"size":{"0":445.5862121582031,"1":59.86365509033203},"flags":{},"order":2,"mode":0,"outputs":[{"name":"SAM_MODEL","type":"SAM_MODEL","links":[1251],"shape":3,"label":"SAM_MODEL","slot_index":0}],"properties":{"Node name for S&R":"SAMModelLoader (segment anything)"},"widgets_values":["sam_vit_b (375MB)"],"serialize_values":[null]},{"id":779,"type":"Crop Face","pos":[-1285,-1315],"size":{"0":406.6036071777344,"1":122},"flags":{},"order":23,"mode":0,"inputs":[{"name":"model","type":"RETINAFACE","link":1395,"label":"model","slot_index":0},{"name":"image","type":"IMAGE","link":1396,"label":"image"}],"outputs":[{"name":"face_image","type":"IMAGE","links":[1397],"shape":3,"label":"face_image","slot_index":0},{"name":"preview","type":"IMAGE","links":[1398],"shape":3,"label":"preview","slot_index":1},{"name":"bbox","type":"BBOX","links":null,"shape":3,"label":"bbox"}],"properties":{"Node name for S&R":"Crop Face"},"widgets_values":[0.7000000000000001,256],"serialize_values":[null,null]},{"id":820,"type":"SaveImage","pos":[2081,420],"size":{"0":834.7745361328125,"1":1017.8824462890625},"flags":{},"order":80,"mode":0,"inputs":[{"name":"images","type":"IMAGE","link":1460,"label":"images"}],"properties":{},"widgets_values":["DragonYear_"],"serialize_values":["DragonYear_"]},{"id":807,"type":"PreviewImage","pos":[-711,-3071],"size":{"0":1246.3797607421875,"1":1573.7523193359375},"flags":{},"order":79,"mode":0,"inputs":[{"name":"images","type":"IMAGE","link":1441,"label":"images"}],"properties":{"Node name for S&R":"PreviewImage"}},{"id":794,"type":"Image Overlay","pos":[1959,-1204],"size":{"0":378.3213195800781,"1":290.0592956542969},"flags":{},"order":72,"mode":0,"inputs":[{"name":"base_image","type":"IMAGE","link":1430,"label":"base_image"},{"name":"overlay_image","type":"IMAGE","link":1426,"label":"overlay_image"},{"name":"optional_mask","type":"MASK","link":1427,"label":"optional_mask"},{"name":"width","type":"INT","link":1428,"widget":{"name":"width"},"label":"width"},{"name":"height","type":"INT","link":1429,"widget":{"name":"height"},"label":"height"}],"outputs":[{"name":"IMAGE","type":"IMAGE","links":[1461,1462],"shape":3,"label":"IMAGE","slot_index":0}],"properties":{"Node name for S&R":"Image Overlay"},"widgets_values":["None","nearest-exact",1,512,512,0,0,0,0],"color":"#332233","bgcolor":"#553333","shape":1,"serialize_values":[null,null,null,null,null,null,null,null,null]},{"id":654,"type":"SDXLPromptStyler","pos":[-1751,-803],"size":{"0":433.7202453613281,"1":402.2193603515625},"flags":{},"order":3,"mode":0,"outputs":[{"name":"text_positive","type":"STRING","links":[1186],"shape":3,"label":"text_positive","slot_index":0},{"name":"text_negative","type":"STRING","links":[1187],"shape":3,"label":"text_negative","slot_index":1}],"properties":{"Node name for S&R":"SDXLPromptStyler"},"widgets_values":["a human,happy,upper_body,focus on face, firecrackers, fireworks, lantern, Chinese festival, dark background, night,depth of field,fcartoon, 3d style, Pixar Animation Studio, simple background, fantastic,solo, unity, masterpiece,best quality,","hand,normal quality,bad quality, worse quality,ugly,signature, ","sai-3d-model",false],"serialize_values":["a human,happy,upper_body,focus on face, firecrackers, fireworks, lantern, Chinese festival, dark background, night,depth of field,fcartoon, 3d style, Pixar Animation Studio, simple background, fantastic,solo, unity, masterpiece,best quality,","hand,normal quality,bad quality, worse quality,ugly,signature, ",null,null]},{"id":821,"type":"PreviewImage","pos":[2452,-1198],"size":{"0":448.765380859375,"1":569.7576293945312},"flags":{},"order":73,"mode":0,"inputs":[{"name":"images","type":"IMAGE","link":1461,"label":"images"}],"properties":{"Node name for S&R":"PreviewImage"}},{"id":432,"type":"LoadImage","pos":[-1823,-3075],"size":{"0":445.1772155761719,"1":714.9067993164062},"flags":{},"order":4,"mode":0,"outputs":[{"name":"IMAGE","type":"IMAGE","links":[1379],"shape":3,"label":"IMAGE","slot_index":0},{"name":"MASK","type":"MASK","links":null,"shape":3,"label":"MASK"}],"title":"\u8f93\u5165\u56fe\u50cf","properties":{"Node name for S&R":"LoadImage"},"widgets_values":["https://bfs.esheep.com/bfs/aikobo-bfs/app/comfy/8aa993e2f3c1f7daaaefe548ac8e4c6ac12c4c61.png@1536w_1536h_0e","image"],"color":"#222","serialize_values":[null,null]},{"id":818,"type":"PrimitiveNode","pos":[-1320,-2517],"size":{"0":210,"1":58},"flags":{},"order":5,"mode":0,"outputs":[{"name":"STRING","type":"STRING","links":[1459],"slot_index":0,"widget":{"name":"value"},"label":"STRING"}],"title":"\u6a2a\u6279\uff085\u4e2a\u5b57\u5185\uff09","properties":{"Run widget replace on values":false},"widgets_values":[null],"serialize_values":[null]},{"id":331,"type":"LoadImage","pos":[-2356,-2235],"size":{"0":459.8890686035156,"1":702.7122192382812},"flags":{},"order":6,"mode":0,"outputs":[{"name":"IMAGE","type":"IMAGE","links":[1399],"shape":3,"label":"IMAGE","slot_index":0},{"name":"MASK","type":"MASK","links":null,"shape":3,"label":"MASK"}],"title":"\u59ff\u52bf","properties":{"Node name for S&R":"LoadImage"},"widgets_values":["https://bfs.esheep.com/bfs/aikobo-bfs/app/comfy/b5568faca348a22828b2fd45deda44d2db72a317.png@1536w_1536h_0e","image"],"color":"#222","serialize_values":[null,null]},{"id":782,"type":"LoadImage","pos":[-1829,-2234.598256645709],"size":{"0":460.81402587890625,"1":701.561279296875},"flags":{},"order":7,"mode":0,"outputs":[{"name":"IMAGE","type":"IMAGE","links":[1403],"shape":3,"label":"IMAGE","slot_index":0},{"name":"MASK","type":"MASK","links":null,"shape":3,"label":"MASK"}],"title":"\u80cc\u666f","properties":{"Node name for S&R":"LoadImage"},"widgets_values":["https://bfs.esheep.com/bfs/aikobo-bfs/app/comfy/29ba93bfa03810997d06b37e225943cd068916b2.png@1536w_1536h_0e","image"],"color":"#222","serialize_values":[null,null]},{"id":793,"type":"LoadImage","pos":[-1328,-2228.598256645709],"size":{"0":454.346435546875,"1":685.1422729492188},"flags":{},"order":8,"mode":0,"outputs":[{"name":"IMAGE","type":"IMAGE","links":[1426],"shape":3,"label":"IMAGE","slot_index":0},{"name":"MASK","type":"MASK","links":[1427],"shape":3,"label":"MASK","slot_index":1}],"title":"\u8fb9\u6846","properties":{"Node name for S&R":"LoadImage"},"widgets_values":["https://bfs.esheep.com/bfs/aikobo-bfs/app/comfy/f0c9b5ac2b1eb95cabfe8292867f9d8d7cff179c.png@1536w_1536h_0e","image"],"serialize_values":[null,null]},{"id":341,"type":"IPAdapterModelLoader","pos":[-1766,-1293],"size":{"0":438.3764343261719,"1":58},"flags":{},"order":9,"mode":0,"outputs":[{"name":"IPADAPTER","type":"IPADAPTER","links":[1100],"shape":3,"slot_index":0,"label":"IPADAPTER"}],"properties":{"Node name for S&R":"IPAdapterModelLoader"},"widgets_values":["ip-adapter-plus-face_sdxl_vit-h.safetensors"],"color":"#222","serialize_values":[null]},{"id":340,"type":"CLIPVisionLoader","pos":[-1764,-1394],"size":{"0":440.12872314453125,"1":58},"flags":{},"order":10,"mode":0,"outputs":[{"name":"CLIP_VISION","type":"CLIP_VISION","links":[1102],"shape":3,"label":"CLIP_VISION","slot_index":0}],"properties":{"Node name for S&R":"CLIPVisionLoader"},"widgets_values":["ip_adaptor_sd15_pytorch_model.bin"],"color":"#222","serialize_values":[null]},{"id":613,"type":"IPAdapterAdvanced","pos":[-1769,-1193],"size":{"0":441.888427734375,"1":258},"flags":{},"order":37,"mode":0,"inputs":[{"name":"ipadapter","type":"IPADAPTER","link":1100,"label":"ipadapter"},{"name":"clip_vision","type":"CLIP_VISION","link":1102,"label":"clip_vision"},{"name":"image","type":"IMAGE","link":1397,"slot_index":2,"label":"image"},{"name":"model","type":"MODEL","link":1469,"label":"model"},{"name":"attn_mask","type":"MASK","link":null,"label":"attn_mask"},{"name":"image_negative","type":"IMAGE","link":"null","label":"image_negative"}],"outputs":[{"name":"MODEL","type":"MODEL","links":[1164,1417],"shape":3,"slot_index":0,"label":"MODEL"}],"properties":{"Node name for S&R":"IPAdapterAdvanced"},"widgets_values":[0.8,"linear","concat",0,1,"V only"],"color":"#222","serialize_values":[null,null,null,null,null,null]},{"id":651,"type":"Reroute","pos":[-1897,-785],"size":[75,26],"flags":{},"order":38,"mode":0,"inputs":[{"name":"","type":"*","link":1470,"label":""}],"outputs":[{"name":"CLIP","type":"CLIP","links":[1172,1173],"slot_index":0,"label":"CLIP"}],"properties":{"showOutputText":true,"horizontal":false}},{"id":826,"type":"LoraLoader","pos":[-2374,-809],"size":{"0":431.005859375,"1":149.77020263671875},"flags":{},"order":33,"mode":0,"inputs":[{"name":"model","type":"MODEL","link":1467,"label":"model"},{"name":"clip","type":"CLIP","link":1468,"label":"clip"}],"outputs":[{"name":"MODEL","type":"MODEL","links":[1469],"shape":3,"label":"MODEL","slot_index":0},{"name":"CLIP","type":"CLIP","links":[1470],"shape":3,"label":"CLIP","slot_index":1}],"properties":{"Node name for S&R":"LoraLoader"},"widgets_values":["Concept Sliders:pixar_style(V1.0)",2,1],"serialize_values":["4301_6322_7409@e07c30e4f8.pt",null,null]},{"id":736,"type":"Reroute","pos":[821.8658425558743,-71.70383029513891],"size":[75,26],"flags":{},"order":20,"mode":0,"inputs":[{"name":"","type":"*","link":1471,"label":""}],"outputs":[{"name":"VAE","type":"VAE","links":[1301,1310],"slot_index":0,"label":"VAE"}],"properties":{"showOutputText":true,"horizontal":false}},{"id":650,"type":"VAEDecode","pos":[-222.47941949759692,-1386.0055556072239],"size":{"0":776.1663818359375,"1":46},"flags":{},"order":53,"mode":0,"inputs":[{"name":"samples","type":"LATENT","link":1168,"label":"samples"},{"name":"vae","type":"VAE","link":1472,"label":"vae","slot_index":1}],"outputs":[{"name":"IMAGE","type":"IMAGE","links":[1175,1421],"shape":3,"label":"IMAGE","slot_index":0}],"properties":{"Node name for S&R":"VAEDecode"}},{"id":823,"type":"CheckpointLoaderSimple","pos":[-2372,-1390],"size":{"0":416.47076416015625,"1":125.53530883789062},"flags":{},"order":11,"mode":0,"outputs":[{"name":"MODEL","type":"MODEL","links":[1464],"shape":3,"label":"MODEL","slot_index":0},{"name":"CLIP","type":"CLIP","links":[1463],"shape":3,"label":"CLIP","slot_index":1},{"name":"VAE","type":"VAE","links":[1471,1472],"shape":3,"label":"VAE","slot_index":2}],"properties":{"Node name for S&R":"CheckpointLoaderSimple"},"widgets_values":["samaritan3dCartoon_V3(SD1.5)"],"serialize_values":["4171_6183_7242@d056a0ac7a.safetensors"]},{"id":825,"type":"LoraLoader","pos":[-2372,-1005],"size":{"0":422.7125549316406,"1":126},"flags":{},"order":27,"mode":0,"inputs":[{"name":"model","type":"MODEL","link":1465,"label":"model"},{"name":"clip","type":"CLIP","link":1466,"label":"clip"}],"outputs":[{"name":"MODEL","type":"MODEL","links":[1467],"shape":3,"label":"MODEL","slot_index":0},{"name":"CLIP","type":"CLIP","links":[1468],"shape":3,"label":"CLIP","slot_index":1}],"properties":{"Node name for S&R":"LoraLoader"},"widgets_values":["Concept Sliders:Fix hands \u4fee\u624b(v1)",3,1],"serialize_values":["3306_4984_5845@d98c482846.pt",null,null]},{"id":824,"type":"LoraLoader","pos":[-2373,-1200],"size":{"0":421.9326477050781,"1":126},"flags":{},"order":19,"mode":0,"inputs":[{"name":"model","type":"MODEL","link":1464,"label":"model"},{"name":"clip","type":"CLIP","link":1463,"label":"clip"}],"outputs":[{"name":"MODEL","type":"MODEL","links":[1465],"shape":3,"label":"MODEL","slot_index":0},{"name":"CLIP","type":"CLIP","links":[1466],"shape":3,"label":"CLIP","slot_index":1}],"properties":{"Node name for S&R":"LoraLoader"},"widgets_values":["Concept Sliders: smiling\u7b11(V1.0)",1,1],"serialize_values":["3248_4906_5737@6430ab4739.pt",null,null]},{"id":802,"type":"Text_Image_Zho","pos":[2082.961191494292,-96.58909803368697],"size":{"0":365.5564880371094,"1":466},"flags":{},"order":24,"mode":0,"inputs":[{"name":"text","type":"STRING","link":1458,"widget":{"name":"text"},"label":"text"}],"outputs":[{"name":"image","type":"IMAGE","links":[1444,1450],"shape":3,"label":"image","slot_index":0}],"properties":{"Node name for S&R":"Text_Image_Zho"},"widgets_values":[null,"\u5e9e\u95e8\u6b63\u9053\u7c97\u4e66\u4f536.0","center",0,120,"#ffddad",4,"#8e0101",0,105,750,512,false,false,100,180,360],"serialize_values":[null,null,null,null,null,null,null,null,null,null,null,null,null,null,null,null,null]},{"id":646,"type":"KSampler","pos":[-752.4794194975968,-1386.0055556072239],"size":{"0":495.1385803222656,"1":803.4698486328125},"flags":{},"order":51,"mode":0,"inputs":[{"name":"model","type":"MODEL","link":1164,"label":"model"},{"name":"positive","type":"CONDITIONING","link":1215,"label":"positive","slot_index":1},{"name":"negative","type":"CONDITIONING","link":1216,"label":"negative","slot_index":2},{"name":"latent_image","type":"LATENT","link":1167,"label":"latent_image","slot_index":3}],"outputs":[{"name":"LATENT","type":"LATENT","links":[1168],"shape":3,"label":"LATENT","slot_index":0}],"properties":{"Node name for S&R":"KSampler"},"widgets_values":[421014244465175,"randomize",20,8,"euler","normal",1],"serialize_values":[null,null,null,null,null,null,null]},{"id":669,"type":"DWPreprocessor","pos":[-1286.6499321831432,-13.045784308348075],"size":{"0":436.654052734375,"1":174},"flags":{},"order":39,"mode":0,"inputs":[{"name":"image","type":"IMAGE","link":1227,"label":"image"},{"name":"resolution","type":"INT","link":1221,"widget":{"name":"resolution"},"label":"resolution"}],"outputs":[{"name":"IMAGE","type":"IMAGE","links":[1201,1424],"shape":3,"label":"IMAGE","slot_index":0},{"name":"POSE_KEYPOINT","type":"POSE_KEYPOINT","links":null,"shape":3,"label":"POSE_KEYPOINT","slot_index":1}],"properties":{"Node name for S&R":"DWPreprocessor"},"widgets_values":["enable","enable","enable",512,"yolox_l.onnx","dw-ll_ucoco_384.onnx"],"serialize_values":[null,null,null,null,null,null]},{"id":689,"type":"PixelPerfectResolution","pos":[-1756.6499321831432,276.95421569165205],"size":{"0":440.8377685546875,"1":100.55912017822266},"flags":{},"order":34,"mode":0,"inputs":[{"name":"original_image","type":"IMAGE","link":1226,"label":"original_image"},{"name":"image_gen_width","type":"INT","link":1218,"widget":{"name":"image_gen_width"},"label":"image_gen_width"},{"name":"image_gen_height","type":"INT","link":1219,"widget":{"name":"image_gen_height"},"label":"image_gen_height"}],"outputs":[{"name":"RESOLUTION (INT)","type":"INT","links":[1221],"shape":3,"label":"RESOLUTION (INT)","slot_index":0}],"properties":{"Node name for S&R":"PixelPerfectResolution"},"widgets_values":[512,512,"Just Resize"],"serialize_values":[null,null,null]},{"id":684,"type":"ControlNetLoader","pos":[-1756.6499321831432,436.95421569165205],"size":{"0":438.6188049316406,"1":58},"flags":{},"order":12,"mode":0,"outputs":[{"name":"CONTROL_NET","type":"CONTROL_NET","links":[1204],"shape":3,"label":"CONTROL_NET"}],"properties":{"Node name for S&R":"ControlNetLoader"},"widgets_values":["thibaud_xl_openpose.safetensors"],"serialize_values":[null]},{"id":774,"type":"ControlNetLoader","pos":[-746.6499321831428,-3.0457843083480793],"size":{"0":384.053955078125,"1":58.88391876220703},"flags":{},"order":13,"mode":0,"outputs":[{"name":"CONTROL_NET","type":"CONTROL_NET","links":[1381],"shape":3,"label":"CONTROL_NET"}],"properties":{"Node name for S&R":"ControlNetLoader"},"widgets_values":["sai_xl_canny_128lora.safetensors"],"serialize_values":[null]},{"id":778,"type":"PixelPerfectResolution","pos":[-747,107],"size":{"0":381.68536376953125,"1":98},"flags":{},"order":36,"mode":0,"inputs":[{"name":"original_image","type":"IMAGE","link":1387,"label":"original_image"},{"name":"image_gen_width","type":"INT","link":1388,"widget":{"name":"image_gen_width"},"label":"image_gen_width"},{"name":"image_gen_height","type":"INT","link":1389,"widget":{"name":"image_gen_height"},"label":"image_gen_height"}],"outputs":[{"name":"RESOLUTION (INT)","type":"INT","links":[1390],"shape":3,"label":"RESOLUTION (INT)","slot_index":0}],"properties":{"Node name for S&R":"PixelPerfectResolution"},"widgets_values":[512,512,"Just Resize"],"serialize_values":[null,null,null]}],"links":[[1100,341,0,613,0,"IPADAPTER"],[1102,340,0,613,1,"CLIP_VISION"],[1164,613,0,646,0,"MODEL"],[1167,649,0,646,3,"LATENT"],[1168,646,0,650,0,"LATENT"],[1172,651,0,647,0,"CLIP"],[1173,651,0,648,0,"CLIP"],[1175,650,0,652,0,"IMAGE"],[1186,654,0,663,0,"STRING"],[1187,654,1,663,1,"STRING"],[1191,663,0,666,0,"STRING"],[1192,663,1,667,0,"STRING"],[1193,666,0,647,1,"STRING"],[1194,667,0,648,1,"STRING"],[1198,670,0,677,0,"IMAGE"],[1201,669,0,681,3,"IMAGE"],[1204,684,0,681,2,"CONTROL_NET"],[1205,647,0,681,0,"CONDITIONING"],[1206,648,0,681,1,"CONDITIONING"],[1215,687,0,646,1,"CONDITIONING"],[1216,688,0,646,2,"CONDITIONING"],[1218,673,0,689,1,"INT"],[1219,673,1,689,2,"INT"],[1221,689,0,669,1,"INT"],[1225,677,0,673,0,"IMAGE"],[1226,677,0,689,0,"IMAGE"],[1227,677,0,669,0,"IMAGE"],[1239,673,0,649,0,"INT"],[1240,673,1,649,1,"INT"],[1248,699,0,695,1,"GROUNDING_DINO_MODEL"],[1250,695,0,700,0,"IMAGE"],[1251,701,0,695,0,"SAM_MODEL"],[1256,695,0,708,0,"IMAGE"],[1269,714,0,716,0,"IMAGE"],[1271,708,0,718,0,"IMAGE"],[1272,718,1,714,2,"MASK"],[1273,718,0,714,1,"IMAGE"],[1274,695,1,720,0,"MASK"],[1275,720,0,708,1,"MASK"],[1284,725,0,726,0,"IMAGE"],[1301,736,0,726,1,"VAE"],[1302,733,0,729,0,"MODEL"],[1303,734,0,729,1,"CONDITIONING"],[1304,735,0,729,2,"CONDITIONING"],[1306,726,0,737,0,"LATENT"],[1308,737,0,729,3,"LATENT"],[1309,729,0,738,0,"LATENT"],[1310,736,0,738,1,"VAE"],[1311,738,0,739,0,"IMAGE"],[1379,432,0,772,0,"*"],[1381,774,0,773,2,"CONTROL_NET"],[1383,681,0,773,0,"CONDITIONING"],[1384,681,1,773,1,"CONDITIONING"],[1385,677,0,775,0,"IMAGE"],[1387,677,0,778,0,"IMAGE"],[1388,673,0,778,1,"INT"],[1389,673,1,778,2,"INT"],[1390,778,0,775,1,"INT"],[1391,775,0,773,3,"IMAGE"],[1392,773,0,687,0,"*"],[1393,773,1,688,0,"*"],[1395,780,0,779,0,"RETINAFACE"],[1396,772,0,779,1,"IMAGE"],[1397,779,0,613,2,"IMAGE"],[1398,779,1,781,0,"IMAGE"],[1399,331,0,670,0,"*"],[1403,782,0,786,0,"*"],[1406,787,0,695,2,"IMAGE"],[1409,715,0,714,3,"INT"],[1410,715,1,714,4,"INT"],[1411,788,0,715,0,"IMAGE"],[1412,788,0,714,0,"IMAGE"],[1413,786,0,788,0,"IMAGE"],[1415,708,0,717,0,"IMAGE"],[1416,714,0,725,0,"*"],[1417,613,0,733,0,"*"],[1418,687,0,734,0,"*"],[1419,688,0,735,0,"*"],[1421,650,0,787,0,"*"],[1423,775,0,790,0,"IMAGE"],[1424,669,0,791,0,"IMAGE"],[1425,738,0,792,0,"*"],[1426,793,0,794,1,"IMAGE"],[1427,793,1,794,2,"MASK"],[1428,795,0,794,3,"INT"],[1429,795,1,794,4,"INT"],[1430,792,0,794,0,"IMAGE"],[1431,792,0,795,0,"IMAGE"],[1441,806,0,807,0,"IMAGE"],[1444,802,0,808,0,"IMAGE"],[1445,808,0,806,1,"IMAGE"],[1446,808,1,806,2,"MASK"],[1448,811,0,810,0,"IMAGE"],[1449,811,0,806,0,"IMAGE"],[1450,802,0,813,0,"IMAGE"],[1453,813,0,812,1,"INT"],[1454,810,0,812,0,"INT"],[1455,812,0,814,0,"INT"],[1456,814,0,806,3,"INT"],[1458,819,0,802,0,"STRING"],[1459,818,0,819,0,"*"],[1460,806,0,820,0,"IMAGE"],[1461,794,0,821,0,"IMAGE"],[1462,794,0,811,0,"*"],[1463,823,1,824,1,"CLIP"],[1464,823,0,824,0,"MODEL"],[1465,824,0,825,0,"MODEL"],[1466,824,1,825,1,"CLIP"],[1467,825,0,826,0,"MODEL"],[1468,825,1,826,1,"CLIP"],[1469,826,0,613,3,"MODEL"],[1470,826,1,651,0,"*"],[1471,823,2,736,0,"*"],[1472,823,2,650,1,"VAE"]],"groups":[{"title":"\u8bc6\u522b\u539f\u56fe IPAdapter","bounding":[-1786,-1472,963,564],"color":"#3f789e","font_size":24,"locked":false},{"title":"\u6a21\u578b\u52a0\u8f7d","bounding":[-2393,-1472,479,856],"color":"#3f789e","font_size":24,"locked":false},{"title":"\u63d0\u793a\u8bcd","bounding":[-1787,-890,967,751],"color":"#3f789e","font_size":24,"locked":false},{"title":"\u4eba\u7269\u5361\u901a\u5316\u751f\u6210","bounding":[-1789,-110,1819,908],"color":"#3f789e","font_size":24,"locked":false},{"title":"\u524d\u540e\u666f\u5408\u6210","bounding":[641,-1473,1220,1153],"color":"#3f789e","font_size":24,"locked":false},{"title":"\u653e\u5927\u56fe\u50cf","bounding":[645,-290,1225,825],"color":"#3f789e","font_size":24,"locked":false},{"title":"\u57fa\u7840\u751f\u6210\u56fe\u50cf","bounding":[-782,-1471,1383,1335],"color":"#3f789e","font_size":24,"locked":false},{"title":"\u5408\u6210\u8fb9\u6846","bounding":[1898,-1473,1083,1151],"color":"#3f789e","font_size":24,"locked":false},{"title":"\u53c2\u8003\u56fe\u533a\uff08\u59ff\u52bf/\u80cc\u666f/\u8fb9\u6846\uff09","bounding":[-2394,-2331,1565,830],"color":"#3f789e","font_size":24,"locked":false},{"title":"\u6dfb\u52a0\u6a2a\u6279\u6587\u5b57","bounding":[1901,-285,1078,1765],"color":"#3f789e","font_size":24,"locked":false}],"config":{},"extra":{},"version":0.4}